cameralogger-0.2.0.data/scripts/camerad.py
cameralogger-0.2.0.data/scripts/test_effects.py
cameralogger-0.2.0.data/scripts/timelapse2.py
cameralogger-0.2.0.data/scripts/timelapse.py
cameralogger-0.2.0.dist-info/RECORD
cameralogger-0.2.0.dist-info/metadata.json
cameralogger-0.2.0.dist-info/WHEEL
cameralogger-0.2.0.dist-info/METADATA
cameralogger-0.2.0.dist-info/DESCRIPTION.rst
cameralogger-0.2.0.dist-info/top_level.txt
cameralogger/pi.py
cameralogger/formatters.py
cameralogger/ffmpeg.py
cameralogger/dummy.py
cameralogger/utils.py
cameralogger/zwo.py
cameralogger/__init__.py
