Metadata-Version: 2.0
Name: cameralogger
Version: 0.2.0
Summary: Tools to record and decorate camera images for timelapses etc.
Home-page: https://github.com/stevemarple/python-cameralogger
Author: Steve Marple
Author-email: s.marple@lancaster.ac.uk
License: GPLv3+
Platform: UNKNOWN
Classifier: Development Status :: 4 - Beta
Classifier: Intended Audience :: Education
Classifier: Intended Audience :: Science/Research
Classifier: Natural Language :: English
Classifier: License :: OSI Approved :: GNU General Public License v3 or later (GPLv3+)
Classifier: Operating System :: OS Independent
Classifier: Programming Language :: Python
Classifier: Programming Language :: Python :: 2
Classifier: Programming Language :: Python :: 2.7
Classifier: Programming Language :: Python :: 3
Classifier: Programming Language :: Python :: 3.3
Classifier: Topic :: Software Development :: Libraries :: Python Modules
Requires-Dist: astral
Requires-Dist: atomiccreate
Requires-Dist: aurorawatchuk
Requires-Dist: numpy (>=1.7)
Requires-Dist: Pillow
